Metadata-Version: 1.0
Name: org-e
Version: 0.5
Summary: Organizes files into folders based on type, declutters your life
Home-page: https://github.com/rsnk96/org-e
Author: rsnk
Author-email: rsnk96@gmail.com
License: UNKNOWN
Keywords: clutter,declutter,organize,sort
Platform: UNKNOWN
